sdic/__init__.py
sdic/constants/__init__.py
sdic/db/__init__.py
sdic/db/base.py
sdic/db/models.py
sdic/exts/__init__.py
sdic/exts/profit.py
sdic/exts/promotion.py
sdic/utils/__init__.py
sdic_gxl-0.9.1.dist-info/METADATA
sdic_gxl-0.9.1.dist-info/WHEEL
sdic_gxl-0.9.1.dist-info/RECORD
