Metadata-Version: 2.3
Name: sdic_gxl
Version: 0.9.1
Summary: 
Author: udo-bit
Author-email: enote_gxl@163.com
Requires-Python: >=3.12
Classifier: Programming Language :: Python :: 3
Classifier: Programming Language :: Python :: 3.12
Classifier: Programming Language :: Python :: 3.13
Requires-Dist: oracledb (>=3.2.0,<4.0.0)
Requires-Dist: pandas (>=2.3.1,<3.0.0)
Requires-Dist: scipy (>=1.16.0,<2.0.0)
Requires-Dist: sqlalchemy (>=2.0.41,<3.0.0)
Requires-Dist: typer (>=0.16.0,<0.17.0)
